{"expireTime":9007200875085238000,"key":"b959d9444cc062c788aa8f1f13d643de","val":{"name":"IMAGE_PROCESSING","inputPaths":["/Users/atedford/Documents/CodingAll2020.nosync/eggegg-mdx/tedfordmedia/content/blog/demo02/banner.png"],"outputDir":"/Users/atedford/Documents/CodingAll2020.nosync/eggegg-mdx/tedfordmedia/public/static/ff4d823aaceb5b7d839a0ce7975e2a9f","args":{"isLazy":false,"operations":[{"outputPath":"e0491/banner.png","args":{"width":180,"cropFocus":17,"toFormat":"png","fit":"cover","background":"rgba(0,0,0,1)"}},{"outputPath":"f4094/banner.png","args":{"width":360,"cropFocus":17,"toFormat":"png","fit":"cover","background":"rgba(0,0,0,1)"}},{"outputPath":"3c17d/banner.png","args":{"width":720,"cropFocus":17,"toFormat":"png","fit":"cover","background":"rgba(0,0,0,1)"}},{"outputPath":"05d05/banner.png","args":{"width":1080,"cropFocus":17,"toFormat":"png","fit":"cover","background":"rgba(0,0,0,1)"}},{"outputPath":"fa6ac/banner.png","args":{"width":1129,"cropFocus":17,"toFormat":"png","fit":"cover","background":"rgba(0,0,0,1)"}}],"pluginOptions":{"base64Width":20,"forceBase64Format":"","useMozJpeg":false,"stripMetadata":true,"lazyImageGeneration":true,"defaultQuality":50,"failOnError":true,"plugins":[]}}}}